LICENSE.txt
MANIFEST.in
ez_setup.py
setup.py
simplui/__init__.py
simplui/button.py
simplui/checkbox.py
simplui/container.py
simplui/dialogue.py
simplui/flow_layout.py
simplui/folding_box.py
simplui/frame.py
simplui/geometry.py
simplui/label.py
simplui/layout.py
simplui/ninepatch.py
simplui/pyglet_utils.py
simplui/shape.py
simplui/slider.py
simplui/text_input.py
simplui/theme.py
simplui/widget.py
simplui.egg-info/PKG-INFO
simplui.egg-info/SOURCES.txt
simplui.egg-info/dependency_links.txt
simplui.egg-info/requires.txt
simplui.egg-info/top_level.txt