Metadata-Version: 1.0
Name: simplui
Version: 1.0.4
Summary: Light-weight GUI toolkit for pyglet
Home-page: http://simplui.googlecode.com/
Author: Tristam MacDonald
Author-email: swiftcoder@gmail.com
License: BSD
Platform: all
Classifier: Intended Audience :: Developers
Classifier: License :: OSI Approved :: BSD License
Classifier: Natural Language :: English
Classifier: Operating System :: OS Independent
Classifier: Programming Language :: Python :: 2
Classifier: Topic :: Scientific/Engineering :: Human Machine Interfaces
Classifier: Topic :: Software Development :: User Interfaces
